fitz_pgserver/__init__.py
fitz_pgserver/_commands.py
fitz_pgserver/postgres_server.py
fitz_pgserver/utils.py
fitz_pgserver-0.1.5.dist-info/METADATA
fitz_pgserver-0.1.5.dist-info/WHEEL
fitz_pgserver-0.1.5.dist-info/licenses/LICENSE
fitz_pgserver-0.1.5.dist-info/RECORD
