Metadata-Version: 2.4
Name: fitz-pgserver
Version: 0.1.5
Summary: Fork of pgserver with Windows crash recovery fix - self-contained PostgreSQL for Python apps
Project-URL: Homepage, https://github.com/yafitzdev/fitz-pgserver
Project-URL: Repository, https://github.com/yafitzdev/fitz-pgserver
Project-URL: Issues, https://github.com/yafitzdev/fitz-pgserver/issues
Project-URL: Upstream, https://github.com/orm011/pgserver
Author: Fitz AI Contributors
Author-email: Oscar Moll <orm@csail.mit.edu>
License-Expression: Apache-2.0
License-File: LICENSE
Keywords: database,embedded,pgserver,pgvector,postgresql,rag
Classifier: Development Status :: 4 - Beta
Classifier: Intended Audience :: Developers
Classifier: License :: OSI Approved :: Apache Software License
Classifier: Operating System :: OS Independent
Classifier: Programming Language :: Python :: 3
Classifier: Programming Language :: Python :: 3.9
Classifier: Programming Language :: Python :: 3.10
Classifier: Programming Language :: Python :: 3.11
Classifier: Programming Language :: Python :: 3.12
Classifier: Topic :: Database
Requires-Python: >=3.9
Requires-Dist: fasteners>=0.19
Requires-Dist: pgserver>=0.1.4
Requires-Dist: platformdirs>=4.0.0
Requires-Dist: psutil>=5.9.0
Provides-Extra: dev
Requires-Dist: psycopg2-binary; extra == 'dev'
Requires-Dist: pytest; extra == 'dev'
Requires-Dist: sqlalchemy>=2; extra == 'dev'
